dwi/__init__.py
dwi/asciifile.py
dwi/autoroi.py
dwi/compat.py
dwi/conf.py
dwi/conf_new.py
dwi/dataset.py
dwi/dicomfile.py
dwi/doit.py
dwi/files.py
dwi/fit.py
dwi/fit_one_by_one.py
dwi/fit_one_by_one_alt.py
dwi/hdf5.py
dwi/image.py
dwi/job.py
dwi/mask.py
dwi/mayavi.py
dwi/minimize.py
dwi/models.py
dwi/nifti.py
dwi/paths.py
dwi/patient.py
dwi/plot.py
dwi/shell.py
dwi/standardize.py
dwi/stats.py
dwi/texture.py
dwi/texture_mahotas.py
dwi/texture_skimage.py
dwi/types.py
dwi/util.py
dwi/ximage.py
dwi/doc/INSTRUCTIONS.md
dwi/doc/autoroi.txt
dwi/doc/data.rst
dwi/doc/spells.txt
dwi/doc/texture.rst
dwi/examples/doit.cfg
dwi/examples/dwilib.cfg
dwi/examples/patients_example.txt
dwi/examples/samples_example.txt
dwi/tools/anonymize_dicom.py
dwi/tools/auc.py
dwi/tools/blackout.py
dwi/tools/boxplot.py
dwi/tools/check_mask_overlap.py
dwi/tools/check_rep_anomalies.py
dwi/tools/classify.py
dwi/tools/correlation.py
dwi/tools/cpr_tool.py
dwi/tools/find_roi.py
dwi/tools/fit.py
dwi/tools/get_labeled.py
dwi/tools/get_texture.py
dwi/tools/grid.py
dwi/tools/histogram.py
dwi/tools/list.py
dwi/tools/list_data.py
dwi/tools/list_voxels.py
dwi/tools/mask_out_dicom.py
dwi/tools/masktool.py
dwi/tools/patient_tool.py
dwi/tools/pcorr.py
dwi/tools/plot_images.py
dwi/tools/pmapinfo.py
dwi/tools/reproducibility.py
dwi/tools/roc_auc.py
dwi/tools/segment.py
dwi/tools/select_voxels.py
dwi/tools/standardize.py
dwi/tools/stats.py
dwi/tools/texture_auc.py
dwi/tools/texture_auc_classify.py
dwi/tools/texture_auc_params.py
dwi/tools/texture_auc_test.py
dwi/tools/texture_auc_test.py.old
dwi/tools/view_dicom.py
dwi/tools/vis.py
dwilib-0.1.8.dev0.dist-info/AUTHORS
dwilib-0.1.8.dev0.dist-info/LICENSE
dwilib-0.1.8.dev0.dist-info/METADATA
dwilib-0.1.8.dev0.dist-info/WHEEL
dwilib-0.1.8.dev0.dist-info/top_level.txt
dwilib-0.1.8.dev0.dist-info/RECORD
