Metadata-Version: 2.1
Name: dwilib
Version: 0.1.8.dev0
Summary: Research tools for MRI-based CAD of cancer
Home-page: https://github.com/jupito/dwilib
Author: Jussi Toivonen
Author-email: jupito@iki.fi
License: MIT
Keywords: medical imaging cancer mri
Platform: UNKNOWN
Classifier: Development Status :: 2 - Pre-Alpha
Classifier: Environment :: Console
Classifier: Intended Audience :: Science/Research
Classifier: License :: OSI Approved :: MIT License
Classifier: Operating System :: POSIX
Classifier: Programming Language :: Python :: 3.4
Classifier: Topic :: Scientific/Engineering :: Image Recognition
Classifier: Topic :: Scientific/Engineering :: Medical Science Apps.
Classifier: Topic :: Utilities
Requires-Python: >=3.4
